LICENSE
LICENSE.md
README.md
setup.py
lapisgs/prepare.py
lapisgs/prepare_reduced.py
lapisgs/render.py
lapisgs/train.py
lapisgs/train_full_pipeline.py
lapisgs/train_full_pipeline_reduced.py
lapisgs/train_reduced.py
lapisgs.egg-info/PKG-INFO
lapisgs.egg-info/SOURCES.txt
lapisgs.egg-info/dependency_links.txt
lapisgs.egg-info/requires.txt
lapisgs.egg-info/top_level.txt
lapisgs/dataset/__init__.py
lapisgs/dataset/colmap.py
lapisgs/dataset/dataset.py
lapisgs/trainer/__init__.py
lapisgs/trainer/combinations.py
lapisgs/trainer/opacity_reset.py
lapisgs/trainer/densifier/__init__.py
lapisgs/trainer/densifier/combinations.py
lapisgs/trainer/densifier/trainer.py
lapisgs/trainer/extensions/reduced_3dgs/__init__.py
lapisgs/trainer/extensions/reduced_3dgs/combinations.py
lapisgs/trainer/extensions/reduced_3dgs/importance.py
lapisgs/trainer/extensions/reduced_3dgs/trainer.py