Metadata-Version: 2.1
Name: lapisgs
Version: 1.0.0
Summary: Refactored python training and inference code for 3D Gaussian Splatting
Home-page: https://github.com/yindaheng98/lapis-gs
Author: yindaheng98
Author-email: yindaheng98@gmail.com
Classifier: Programming Language :: Python :: 3
License-File: LICENSE
License-File: LICENSE.md
